lidar_pcd_saver-0.1.0.dist-info/licenses/LICENCE
lidartopcd/__init__.py
lidartopcd/saver.py
lidar_pcd_saver-0.1.0.dist-info/METADATA
lidar_pcd_saver-0.1.0.dist-info/WHEEL
lidar_pcd_saver-0.1.0.dist-info/entry_points.txt
lidar_pcd_saver-0.1.0.dist-info/top_level.txt
lidar_pcd_saver-0.1.0.dist-info/RECORD
