Metadata-Version: 2.4
Name: lidar-pcd-saver
Version: 0.1.0
Summary: A ROS2 tool to save PCD files from LiDAR subscriptions with configurable processing
Author-email: Your Name <your.email@example.com>
Classifier: Programming Language :: Python :: 3
Classifier: License :: OSI Approved :: MIT License
Classifier: Operating System :: OS Independent
Requires-Python: >=3.8
License-File: LICENCE
Requires-Dist: numpy
Requires-Dist: scipy
Dynamic: license-file
